chromadb-1.3.7.dist-info/METADATA
chromadb-1.3.7.dist-info/WHEEL
chromadb-1.3.7.dist-info/entry_points.txt
chromadb-1.3.7.dist-info/licenses/LICENSE
chromadb/__init__.py
chromadb/api/__init__.py
chromadb/api/async_api.py
chromadb/api/async_client.py
chromadb/api/async_fastapi.py
chromadb/api/base_http_client.py
chromadb/api/client.py
chromadb/api/collection_configuration.py
chromadb/api/configuration.py
chromadb/api/fastapi.py
chromadb/api/functions.py
chromadb/api/models/AsyncCollection.py
chromadb/api/models/AttachedFunction.py
chromadb/api/models/Collection.py
chromadb/api/models/CollectionCommon.py
chromadb/api/rust.py
chromadb/api/segment.py
chromadb/api/shared_system_client.py
chromadb/api/types.py
chromadb/app.py
chromadb/auth/__init__.py
chromadb/auth/basic_authn/__init__.py
chromadb/auth/simple_rbac_authz/__init__.py
chromadb/auth/token_authn/__init__.py
chromadb/auth/utils/__init__.py
chromadb/base_types.py
chromadb/chromadb_rust_bindings.pyi
chromadb/cli/__init__.py
chromadb/cli/cli.py
chromadb/cli/utils.py
chromadb/config.py
chromadb/db/__init__.py
chromadb/db/base.py
chromadb/db/impl/__init__.py
chromadb/db/impl/grpc/client.py
chromadb/db/impl/grpc/server.py
chromadb/db/impl/sqlite.py
chromadb/db/impl/sqlite_pool.py
chromadb/db/migrations.py
chromadb/db/mixins/embeddings_queue.py
chromadb/db/mixins/sysdb.py
chromadb/db/system.py
chromadb/errors.py
chromadb/execution/__init__.py
chromadb/execution/executor/abstract.py
chromadb/execution/executor/distributed.py
chromadb/execution/executor/local.py
chromadb/execution/expression/__init__.py
chromadb/execution/expression/operator.py
chromadb/execution/expression/plan.py
chromadb/experimental/density_relevance.ipynb
chromadb/ingest/__init__.py
chromadb/ingest/impl/utils.py
chromadb/log_config.yml
chromadb/logservice/logservice.py
chromadb/migrations/__init__.py
chromadb/migrations/embeddings_queue/00001-embeddings.sqlite.sql
chromadb/migrations/embeddings_queue/00002-embeddings-queue-config.sqlite.sql
chromadb/migrations/metadb/00001-embedding-metadata.sqlite.sql
chromadb/migrations/metadb/00002-embedding-metadata.sqlite.sql
chromadb-1.3.7.dist-info/RECORD
